Metadata-Version: 2.1
Name: feishu-p1
Version: 1.0.3
Summary: Feishu Third-party Libraries
Home-page: https://github.com/tutan123/feishu-p1
Author: tutu
Author-email: tutu@gmail.com
Classifier: Programming Language :: Python :: 2.7
Classifier: Programming Language :: Python :: 3
Classifier: License :: OSI Approved :: MIT License
Requires-Python: >=2.7
License-File: LICENSE
Requires-Dist: urllib3
Requires-Dist: requests
